robocodeai.py
robocodeai-0.0.5.dist-info/METADATA
robocodeai-0.0.5.dist-info/WHEEL
robocodeai-0.0.5.dist-info/top_level.txt
robocodeai-0.0.5.dist-info/RECORD
