Metadata-Version: 2.1
Name: robocodeai
Version: 0.0.5
Summary: Support package
Author-email: Artem Ljukshin <garo109696@gmail.com>
Classifier: Operating System :: OS Independent
Requires-Python: >=3.11
Requires-Dist: g4f[all] >=0.3.2.7
